django_country_filter/__init__.py
django_country_filter/provider.py
django_country_filter/providers/__init__.py
django_country_filter/providers/ip2c.py
tests/mocks/__init__.py
tests/mocks/provider_mock.py
tests/providers/__init__.py
tests/providers/tests_ip2c.py
django_country_filter-0.0.1.dist-info/LICENSE
django_country_filter-0.0.1.dist-info/METADATA
django_country_filter-0.0.1.dist-info/WHEEL
django_country_filter-0.0.1.dist-info/top_level.txt
django_country_filter-0.0.1.dist-info/RECORD
