Metadata-Version: 2.1
Name: django-country-filter
Version: 0.0.1
Summary: Django middleware country filter.
Home-page: https://github.com/0p4ul0/django-country-filter
Author: Paulo Roberto
Author-email: paulo.pinda@gmail.com
License: UNKNOWN
Platform: UNKNOWN
Classifier: Programming Language :: Python :: 3
Classifier: License :: OSI Approved :: MIT License
Classifier: Operating System :: OS Independent
Requires-Python: >=3.6
Requires-Dist: requests
Requires-Dist: django (==2.2.13)
